stempel/__init__.py
stempel/egothor.py
stempel/stemmer_20000.tbl.gz
stempel/stemmer_polimorf.tbl.gz
stempel/streams.py
pystempel-1.2.0.dist-info/LICENSE.txt
pystempel-1.2.0.dist-info/METADATA
pystempel-1.2.0.dist-info/WHEEL
pystempel-1.2.0.dist-info/top_level.txt
pystempel-1.2.0.dist-info/RECORD
