Metadata-Version: 1.2
Name: pystempel
Version: 1.2.0
Summary: Polish stemmer.
Home-page: https://github.com/dzieciou/pystempel
Author: Maciej Gawinecki
Author-email: mgawinecki@gmail.com
License: See documentation
Project-URL: Source, https://github.com/dzieciou/pystempel
Keywords: NLP,natural language processing,computational linguistics,stemming,linguistics,language,natural language,text analytics
Platform: UNKNOWN
Classifier: Intended Audience :: Developers
Classifier: Intended Audience :: Education
Classifier: Intended Audience :: Information Technology
Classifier: Intended Audience :: Science/Research
Classifier: Operating System :: POSIX :: Linux
Classifier: Operating System :: MacOS :: MacOS X
Classifier: Operating System :: Microsoft :: Windows
Classifier: Programming Language :: Python :: 3
Classifier: Programming Language :: Python :: 3.5
Classifier: Programming Language :: Python :: 3 :: Only
Classifier: Topic :: Scientific/Engineering
Classifier: Topic :: Scientific/Engineering :: Artificial Intelligence
Classifier: Topic :: Scientific/Engineering :: Human Machine Interfaces
Classifier: Topic :: Scientific/Engineering :: Information Analysis
Classifier: Topic :: Text Processing
Classifier: Topic :: Text Processing :: General
Classifier: Topic :: Text Processing :: Linguistic
Requires-Python: >=3.5
